README.txt
setup.cfg
setup.py
Products/__init__.py
Products.introspector.egg-info/PKG-INFO
Products.introspector.egg-info/SOURCES.txt
Products.introspector.egg-info/dependency_links.txt
Products.introspector.egg-info/entry_points.txt
Products.introspector.egg-info/namespace_packages.txt
Products.introspector.egg-info/not-zip-safe
Products.introspector.egg-info/requires.txt
Products.introspector.egg-info/top_level.txt
Products/introspector/__init__.py
Products/introspector/forms.py
Products/introspector/interfaces.py
