Metadata-Version: 1.0
Name: Products.introspector
Version: 0.1dev
Summary: A handy tool for inspecting Plone databases
Home-page: UNKNOWN
Author: Daniel Greenfeld
Author-email: pydanny@gmail.com
License: GPL
Platform: UNKNOWN
Classifier: Programming Language :: Python
Classifier: Topic :: Software Development :: Libraries :: Python Modules
